myflaskutil/__init__.py
myflaskutil/app.py
myflaskutil-0.1.0.dist-info/METADATA
myflaskutil-0.1.0.dist-info/WHEEL
myflaskutil-0.1.0.dist-info/top_level.txt
myflaskutil-0.1.0.dist-info/RECORD
