Metadata-Version: 2.1
Name: myflaskutil
Version: 0.1.0
Requires-Dist: Flask
